publicdata_ca/__init__.py
publicdata_ca/catalog.py
publicdata_ca/cli.py
publicdata_ca/datasets.py
publicdata_ca/http.py
publicdata_ca/http_cache.py
publicdata_ca/manifest.py
publicdata_ca/normalize.py
publicdata_ca/profiles.py
publicdata_ca/provenance.py
publicdata_ca/provider.py
publicdata_ca/url_cache.py
publicdata_ca/providers/__init__.py
publicdata_ca/providers/boc_valet.py
publicdata_ca/providers/ckan.py
publicdata_ca/providers/cmhc.py
publicdata_ca/providers/open_canada.py
publicdata_ca/providers/sdmx.py
publicdata_ca/providers/socrata.py
publicdata_ca/providers/statcan.py
publicdata_ca/resolvers/__init__.py
publicdata_ca/resolvers/cmhc_landing.py
publicdata_ca-0.1.0.dist-info/licenses/LICENSE
publicdata_ca-0.1.0.dist-info/METADATA
publicdata_ca-0.1.0.dist-info/WHEEL
publicdata_ca-0.1.0.dist-info/entry_points.txt
publicdata_ca-0.1.0.dist-info/top_level.txt
publicdata_ca-0.1.0.dist-info/RECORD
