Metadata-Version: 2.4
Name: publicdata-ca
Version: 0.1.0
Summary: A lightweight Python package for discovering, resolving, and downloading Canadian public datasets.
Author: Drew Harris
Maintainer: Drew Harris
License: MIT License
Project-URL: Homepage, https://github.com/ajharris/publicdata_ca
Project-URL: Documentation, https://github.com/ajharris/publicdata_ca/tree/main/docs
Project-URL: Repository, https://github.com/ajharris/publicdata_ca
Project-URL: Issues, https://github.com/ajharris/publicdata_ca/issues
Project-URL: Changelog, https://github.com/ajharris/publicdata_ca/blob/main/CHANGELOG.md
Keywords: canada,open-data,statcan,statistics-canada,cmhc,open-canada,ckan,data-catalog,data-download,canadian-data
Classifier: Development Status :: 3 - Alpha
Classifier: Intended Audience :: Developers
Classifier: Intended Audience :: Science/Research
Classifier: License :: OSI Approved :: MIT License
Classifier: Operating System :: OS Independent
Classifier: Programming Language :: Python :: 3
Classifier: Programming Language :: Python :: 3.9
Classifier: Programming Language :: Python :: 3.10
Classifier: Programming Language :: Python :: 3.11
Classifier: Programming Language :: Python :: 3.12
Classifier: Topic :: Scientific/Engineering :: Information Analysis
Classifier: Topic :: Software Development :: Libraries :: Python Modules
Classifier: Typing :: Typed
Requires-Python: >=3.9
License-File: LICENSE
Requires-Dist: pandas>=2.2
Requires-Dist: requests>=2.31.0
Provides-Extra: dev
Requires-Dist: pytest>=8.2; extra == "dev"
Requires-Dist: pytest-cov>=4.1; extra == "dev"
Dynamic: license-file
